thoth/glyph/__init__.py
thoth/glyph/cli.py
thoth/glyph/constants.py
thoth/glyph/exceptions.py
thoth/glyph/formatter.py
thoth/glyph/lib.py
thoth/glyph/models.py
thoth/glyph/py.typed
thoth/glyph/data/commits-labeled.txt
thoth/glyph/data/commits.train
thoth/glyph/data/model_commits_v2_quant.bin
thoth_glyph-0.1.5.dist-info/METADATA
thoth_glyph-0.1.5.dist-info/RECORD
thoth_glyph-0.1.5.dist-info/WHEEL
thoth_glyph-0.1.5.dist-info/entry_points.txt
thoth_glyph-0.1.5.dist-info/top_level.txt
