Metadata-Version: 2.1
Name: thoth-glyph
Version: 0.1.5
Summary: Generate CHANGELOG entries out of commit messages using AI/ML techniques
Home-page: https://github.com/thoth-station/glyph
Author: Tushar Sharma
Author-email: tussharm@redhat.com
License: GPLv3+
Download-URL: https://pypi.org/project/glyph
Platform: UNKNOWN
Requires-Dist: click
Requires-Dist: thoth-common
Requires-Dist: pandas
Requires-Dist: pygit2
Requires-Dist: fasttext
